numerical-derivative-checker/__init__.py
numerical-derivative-checker/examples.py
numerical-derivative-checker/helper_functions.py
numerical-derivative-checker/numerical_derivative_checker.py
numerical_derivative_checker/__init__.py
numerical_derivative_checker/examples.py
numerical_derivative_checker/helper_functions.py
numerical_derivative_checker/numerical_derivative_checker.py
numerical_derivative_checker-0.8.dist-info/LICENSE
numerical_derivative_checker-0.8.dist-info/METADATA
numerical_derivative_checker-0.8.dist-info/WHEEL
numerical_derivative_checker-0.8.dist-info/top_level.txt
numerical_derivative_checker-0.8.dist-info/RECORD
