Metadata-Version: 2.1
Name: numerical-derivative-checker
Version: 0.8
Summary: Simple numerical derivative checker with randomized input sampling.
Home-page: https://github.com/etpr/numerical_derivative_checker
Author: etpr
Author-email: englertpr@gmail.com
License: MIT
Platform: UNKNOWN
Requires-Python: >=3.7
Requires-Dist: numpy
